imgclass/__init__.py
imgclass/pred.py
imgclass/prepro.py
imgclass/result.py
imgclass/testing.py
imgclass/training.py
imgclass-0.2.1.dist-info/METADATA
imgclass-0.2.1.dist-info/WHEEL
imgclass-0.2.1.dist-info/top_level.txt
imgclass-0.2.1.dist-info/RECORD
