Metadata-Version: 2.1
Name: imgclass
Version: 0.2.1
Summary: 修复result的 plt-tsne
Home-page: https://github.com/zheng-oh/imgclass
Author: ZXING
Author-email: zxing_oh@163.com
Classifier: Programming Language :: Python :: 3
Classifier: License :: OSI Approved :: MIT License
Classifier: Operating System :: OS Independent
Requires-Python: >=3.10
Requires-Dist: matplotlib>=3.9.3
Requires-Dist: numpy>=2.1.3
Requires-Dist: scikit-learn>=1.5.2
Requires-Dist: setuptools>=75.1.0
Requires-Dist: torch>=2.5.1
Requires-Dist: torchvision>=0.20.1
